MANIFEST.in
README.rst
setup.py
examples/Arun2005.py
examples/inspiral.py
examples/spectroscopy.py
examples/tutorial.ipynb
fishergw/__init__.py
fishergw/constants.py
fishergw.egg-info/PKG-INFO
fishergw.egg-info/SOURCES.txt
fishergw.egg-info/dependency_links.txt
fishergw.egg-info/not-zip-safe
fishergw.egg-info/requires.txt
fishergw.egg-info/top_level.txt
fishergw/cosmology/__init__.py
fishergw/cosmology/utils.py
fishergw/detector/README.rst
fishergw/detector/aligo_asd.txt
fishergw/detector/ce_asd.txt
fishergw/detector/etd_asd.txt
fishergw/detector/lisa_asd.txt
fishergw/ringdown/__init__.py
fishergw/ringdown/fisher.py
fishergw/ringdown/harmonics.py
fishergw/ringdown/modified_gr.py
fishergw/ringdown/utils.py
fishergw/ringdown/waveform.py
fishergw/ringdown/qnm_data/210.dat
fishergw/ringdown/qnm_data/220.dat
fishergw/ringdown/qnm_data/221.dat
fishergw/ringdown/qnm_data/330.dat
fishergw/ringdown/qnm_data/440.dat
fishergw/taylorf2/README.rst
fishergw/taylorf2/__init__.py
fishergw/taylorf2/fisher.py
fishergw/taylorf2/waveform.py