Metadata-Version: 1.0
Name: fishergw
Version: 0.0.3
Summary: A Python package to compute Fisher matrices for gravitational wave models
Home-page: https://github.com/costa-pacilio/fishergw.git
Author: Costantino Pacilio
Author-email: costantinopacilio1990@gmail.com
License: MIT
Platform: UNKNOWN
